anedya/__init__.py
anedya/anedya.py
anedya/config.py
anedya/errors.py
anedya/models.py
anedya/transaction.py
anedya/client/__init__.py
anedya/client/bindDevice.py
anedya/client/callbacks.py
anedya/client/certs.py
anedya/client/commandsNext.py
anedya/client/commandsUpdate.py
anedya/client/mqttHandlers.py
anedya/client/submitData.py
anedya/client/submitLogs.py
anedya/client/timeSync.py
anedya_dev_sdk-0.1.10.dist-info/licenses/LICENSE
anedya_dev_sdk-0.1.10.dist-info/METADATA
anedya_dev_sdk-0.1.10.dist-info/WHEEL
anedya_dev_sdk-0.1.10.dist-info/top_level.txt
anedya_dev_sdk-0.1.10.dist-info/RECORD
