Metadata-Version: 2.4
Name: anedya-dev-sdk
Version: 0.1.10
Summary: Anedya python based SDK for IoT devices. This SDK streamlines connectivity with Anedya platform. As this SDK is in Beta release, future versions may have breaking changes.
Home-page: https://github.com/anedyaio/anedya-dev-sdk-python
Author: Anedya Systems
Author-email: support@anedya.io
License: Apache License 2.0
Project-URL: Documentation, https://docs.anedya.io
Project-URL: Release notes, https://github.com/anedyaio/anedya-dev-sdk-python/blob/main/HISTORY.md
Project-URL: Source, https://github.com/anedyaio/anedya-dev-sdk-python
Classifier: Development Status :: 4 - Beta
Classifier: Intended Audience :: Developers
Classifier: License :: OSI Approved :: Apache Software License
Classifier: Operating System :: OS Independent
Classifier: Programming Language :: Python :: 3.7
Classifier: Programming Language :: Python :: 3.8
Classifier: Programming Language :: Python :: 3.9
Classifier: Programming Language :: Python :: 3.10
Classifier: Topic :: Software Development :: Libraries :: Python Modules
License-File: LICENSE
Requires-Dist: requests
Requires-Dist: paho-mqtt>=2.0.0
Dynamic: description-content-type
Dynamic: license-file
